{
    "books": [
        {
            "id": 1,
            "name": "Primeiro livro",
            "price": 25.50,
            "img": "bookImg",
            "description": "Lorem ipsum dolor sit amet, consectetur adipiscing elit, sed do eiusmod tempor incididunt ut labore et dolore magna aliqua. Ut enim ad minim veniam, quis nostrud exercitation ullamco laboris nisi ut aliquip ex ea commodo consequat.",
            "stock": 5
        },
        {
            "id": 2,
            "name": "Segundo livro",
            "price": 25.50,
            "img": "bookImg",
            "description": "Lorem ipsum dolor sit amet, consectetur adipiscing elit, sed do eiusmod tempor incididunt ut labore et dolore magna aliqua. Ut enim ad minim veniam, quis nostrud exercitation ullamco laboris nisi ut aliquip ex ea commodo consequat.",
            "stock": 5
        },
        {
            "id": 3,
            "name": "Terceiro livro",
            "price": 25.50,
            "img": "bookImg",
            "description": "Lorem ipsum dolor sit amet, consectetur adipiscing elit, sed do eiusmod tempor incididunt ut labore et dolore magna aliqua. Ut enim ad minim veniam, quis nostrud exercitation ullamco laboris nisi ut aliquip ex ea commodo consequat.",
            "stock": 5
        },
        {
            "id": 4,
            "name": "Quarto livro",
            "price": 25.50,
            "img": "bookImg",
            "description": "Lorem ipsum dolor sit amet, consectetur adipiscing elit, sed do eiusmod tempor incididunt ut labore et dolore magna aliqua. Ut enim ad minim veniam, quis nostrud exercitation ullamco laboris nisi ut aliquip ex ea commodo consequat.",
            "stock": 5
        },
        {
            "id": 5,
            "name": "Quinto livro",
            "price": 25.50,
            "img": "bookImg",
            "description": "Lorem ipsum dolor sit amet, consectetur adipiscing elit, sed do eiusmod tempor incididunt ut labore et dolore magna aliqua. Ut enim ad minim veniam, quis nostrud exercitation ullamco laboris nisi ut aliquip ex ea commodo consequat.",
            "stock": 5
        }
    ]
}